monoscope_django/__init__.py
monoscope_django-1.0.3.dist-info/METADATA
monoscope_django-1.0.3.dist-info/WHEEL
monoscope_django-1.0.3.dist-info/top_level.txt
monoscope_django-1.0.3.dist-info/RECORD
