Metadata-Version: 2.4
Name: monoscope-django
Version: 1.0.3
Summary: A Django SDK for Monoscope integration
Author: monoscope
Author-email: hello@apitoolkit.io
Requires-Dist: Django
Requires-Dist: monoscope-common
Requires-Dist: opentelemetry-api>=1.0.0
Dynamic: author
Dynamic: author-email
Dynamic: description
Dynamic: description-content-type
Dynamic: requires-dist
Dynamic: summary
